[{
    "id": 1,
    "title": "Card1",
    "description": "Guntar",
    "image": "https://i.ibb.co/hMStH7r/pexels-kaboompics-com-6469.jpg"
  }, {
    "id": 2,
    "title": "Card2",
    "description": "Diarmid",
    "image": "https://i.ibb.co/0f7wFSg/pexels-pixabay-265667.jpg"
  }, {
    "id": 3,
    "title": "Card3",
    "description": "Edsel",
    "image": "https://i.ibb.co/1Tm4gR2/pexels-bruno-bueno-3854816.jpg"
  }, {
    "id": 4,
    "title": "Mattheus",
    "description": "Yolane",
    "image": "Aymer"
  }, {
    "id": 5,
    "title": "Alfie",
    "description": "Zane",
    "image": "Horace"
  }, {
    "id": 6,
    "title": "Tova",
    "description": "Vannie",
    "image": "Ellie"
  }, {
    "id": 7,
    "title": "Debi",
    "description": "Care",
    "image": "Laureen"
  }, {
    "id": 8,
    "title": "Allis",
    "description": "Rancell",
    "image": "Rhodia"
  }, {
    "id": 9,
    "title": "Adi",
    "description": "Myrle",
    "image": "Farica"
  }, {
    "id": 10,
    "title": "Norry",
    "description": "Audre",
    "image": "Clo"
  }]